 
{
    "SystemMenu": [
        {
            "id": "System.volume",
            "type": "IntegerMenuItem",
            "title": "Volume"
        },
        {
            "id": "System.brightness",
            "type": "IntegerMenuItem",
            "title": "Brightness"
        },
        {
            "id": "System.screenRefresh",
            "type": "IntegerMenuItem",
            "title": "Screen Refresh Rate"
        },
        {
            "id": "System.showFPS",
            "type": "BooleanMenuItem",
            "title": "showFPS"
        },
        {
            "id": "System.overclock",
            "type": "MultiOptionMenuItem",
            "title": "Overclock",
            "options": ["840 MHz", "1008 MHz", "1296 MHz"]
        },
        {
            "id": "System.theme",
            "type": "MultiOptionMenuItem",
            "title": "Theme",
            "options": ["Comicbook", "Simplermenu", "BigCody"]
        },
        {
            "id": "System.usbMode",
            "type": "BooleanMenuItem",
            "title": "USB Mode"
        },
        {
            "id": "System.wifi",
            "type": "BooleanMenuItem",
            "title": "WIFI"
        },
        {
            "id": "System.rotation",
            "type": "BooleanMenuItem",
            "title": "Auto rotate"
        },
        {
            "id": "System.quit",
            "type": "SimpleMenuItem",
            "title": "Quit"
        }
    ]
}
